rdsdataapi.py
sqlalchemy_rdsdataapi.py
rdsdataapi-0.1.1.dist-info/METADATA
rdsdataapi-0.1.1.dist-info/WHEEL
rdsdataapi-0.1.1.dist-info/entry_points.txt
rdsdataapi-0.1.1.dist-info/top_level.txt
rdsdataapi-0.1.1.dist-info/RECORD
