Metadata-Version: 2.1
Name: rdsdataapi
Version: 0.1.1
Summary: DBAPI 2.0 adapter & SqlAlchemy Dialect for the RDS Data API
Home-page: https://github.com/dschep/rdsdataapi
Author: Daniel Schep
Author-email: dschep@gmail.com
License: MIT
Platform: UNKNOWN
Classifier: License :: OSI Approved :: MIT License
Classifier: Programming Language :: Python
Classifier: Programming Language :: Python :: 3
Classifier: Programming Language :: Python :: 3.6
Classifier: Programming Language :: Python :: 3.7
Classifier: Programming Language :: Python :: Implementation :: CPython
Classifier: Development Status :: 3 - Alpha
Classifier: Topic :: Database
Classifier: Topic :: Database :: Front-Ends
Requires-Python: >=3.6.0
Requires-Dist: boto3
Provides-Extra: sqlalchemy
Requires-Dist: sqlalchemy ; extra == 'sqlalchemy'
